{"numTotalTestSuites":2,"numPassedTestSuites":2,"numFailedTestSuites":0,"numPendingTestSuites":0,"numTotalTests":24,"numPassedTests":24,"numFailedTests":0,"numPendingTests":0,"numTodoTests":0,"snapshot":{"added":0,"failure":false,"filesAdded":0,"filesRemoved":0,"filesRemovedList":[],"filesUnmatched":0,"filesUpdated":0,"matched":0,"total":0,"unchecked":0,"uncheckedKeysByFile":[],"unmatched":0,"updated":0,"didUpdate":false},"startTime":1778082977798,"success":true,"testResults":[{"assertionResults":[{"ancestorTitles":["Exercício 01"],"fullName":"Exercício 01 Ex01 - Válida - Questão 1","status":"passed","title":"Ex01 - Válida - Questão 1","duration":2.4392660000000035,"failureMessages":[],"meta":{},"tags":[]},{"ancestorTitles":["Exercício 01"],"fullName":"Exercício 01 Ex01 - Correta - Questão 1","status":"passed","title":"Ex01 - Correta - Questão 1","duration":1.034181999999987,"failureMessages":[],"meta":{},"tags":[]},{"ancestorTitles":["Exercício 01"],"fullName":"Exercício 01 Ex01 - Válida - Questão 2","status":"passed","title":"Ex01 - Válida - Questão 2","duration":0.2519920000000013,"failureMessages":[],"meta":{},"tags":[]},{"ancestorTitles":["Exercício 01"],"fullName":"Exercício 01 Ex01 - Correta - Questão 2","status":"passed","title":"Ex01 - Correta - Questão 2","duration":0.38136299999999324,"failureMessages":[],"meta":{},"tags":[]},{"ancestorTitles":["Exercício 01"],"fullName":"Exercício 01 Ex01 - Válida - Questão 3","status":"passed","title":"Ex01 - Válida - Questão 3","duration":0.23684800000000905,"failureMessages":[],"meta":{},"tags":[]},{"ancestorTitles":["Exercício 01"],"fullName":"Exercício 01 Ex01 - Correta - Questão 3","status":"passed","title":"Ex01 - Correta - Questão 3","duration":0.37697,"failureMessages":[],"meta":{},"tags":[]},{"ancestorTitles":["Exercício 01"],"fullName":"Exercício 01 Ex01 - Válida - Questão 4","status":"passed","title":"Ex01 - Válida - Questão 4","duration":0.2767889999999795,"failureMessages":[],"meta":{},"tags":[]},{"ancestorTitles":["Exercício 01"],"fullName":"Exercício 01 Ex01 - Correta - Questão 4","status":"passed","title":"Ex01 - Correta - Questão 4","duration":0.277134000000018,"failureMessages":[],"meta":{},"tags":[]},{"ancestorTitles":["Exercício 01"],"fullName":"Exercício 01 Ex01 - Válida - Questão 5","status":"passed","title":"Ex01 - Válida - Questão 5","duration":0.6069300000000055,"failureMessages":[],"meta":{},"tags":[]},{"ancestorTitles":["Exercício 01"],"fullName":"Exercício 01 Ex01 - Correta - Questão 5","status":"passed","title":"Ex01 - Correta - Questão 5","duration":0.35122100000000955,"failureMessages":[],"meta":{},"tags":[]},{"ancestorTitles":["Exercício 01"],"fullName":"Exercício 01 Ex01 - Válida - Questão 6","status":"passed","title":"Ex01 - Válida - Questão 6","duration":0.27786599999998884,"failureMessages":[],"meta":{},"tags":[]},{"ancestorTitles":["Exercício 01"],"fullName":"Exercício 01 Ex01 - Correta - Questão 6","status":"passed","title":"Ex01 - Correta - Questão 6","duration":0.23008400000000506,"failureMessages":[],"meta":{},"tags":[]},{"ancestorTitles":["Exercício 01"],"fullName":"Exercício 01 Ex01 - Válida - Questão 7","status":"passed","title":"Ex01 - Válida - Questão 7","duration":0.15329399999998827,"failureMessages":[],"meta":{},"tags":[]},{"ancestorTitles":["Exercício 01"],"fullName":"Exercício 01 Ex01 - Correta - Questão 7","status":"passed","title":"Ex01 - Correta - Questão 7","duration":0.2108699999999999,"failureMessages":[],"meta":{},"tags":[]},{"ancestorTitles":["Exercício 01"],"fullName":"Exercício 01 Ex01 - Válida - Questão 8","status":"passed","title":"Ex01 - Válida - Questão 8","duration":0.13639399999999569,"failureMessages":[],"meta":{},"tags":[]},{"ancestorTitles":["Exercício 01"],"fullName":"Exercício 01 Ex01 - Correta - Questão 8","status":"passed","title":"Ex01 - Correta - Questão 8","duration":0.5623800000000188,"failureMessages":[],"meta":{},"tags":[]},{"ancestorTitles":["Exercício 01"],"fullName":"Exercício 01 Ex01 - Válida - Questão 9","status":"passed","title":"Ex01 - Válida - Questão 9","duration":0.1609279999999842,"failureMessages":[],"meta":{},"tags":[]},{"ancestorTitles":["Exercício 01"],"fullName":"Exercício 01 Ex01 - Correta - Questão 9","status":"passed","title":"Ex01 - Correta - Questão 9","duration":0.1898209999999949,"failureMessages":[],"meta":{},"tags":[]},{"ancestorTitles":["Exercício 01"],"fullName":"Exercício 01 Ex01 - Válida - Questão 10","status":"passed","title":"Ex01 - Válida - Questão 10","duration":0.14045300000000793,"failureMessages":[],"meta":{},"tags":[]},{"ancestorTitles":["Exercício 01"],"fullName":"Exercício 01 Ex01 - Correta - Questão 10","status":"passed","title":"Ex01 - Correta - Questão 10","duration":0.4240690000000029,"failureMessages":[],"meta":{},"tags":[]},{"ancestorTitles":["Exercício 01"],"fullName":"Exercício 01 Ex01 - Válida - Questão 11","status":"passed","title":"Ex01 - Válida - Questão 11","duration":0.14162199999998393,"failureMessages":[],"meta":{},"tags":[]},{"ancestorTitles":["Exercício 01"],"fullName":"Exercício 01 Ex01 - Correta - Questão 11","status":"passed","title":"Ex01 - Correta - Questão 11","duration":0.288755000000009,"failureMessages":[],"meta":{},"tags":[]},{"ancestorTitles":["Exercício 01"],"fullName":"Exercício 01 Ex01 - Válida - Questão 12","status":"passed","title":"Ex01 - Válida - Questão 12","duration":0.13314099999999485,"failureMessages":[],"meta":{},"tags":[]},{"ancestorTitles":["Exercício 01"],"fullName":"Exercício 01 Ex01 - Correta - Questão 12","status":"passed","title":"Ex01 - Correta - Questão 12","duration":0.5146119999999996,"failureMessages":[],"meta":{},"tags":[]}],"startTime":1778082978039,"endTime":1778082978049.5146,"status":"passed","message":"","name":"/home/vmca/Code/school/atv_pub/2d-05-funcoes/ex01.test.js"}]}